tracr/__init__.py
tracr/compiler/__init__.py
tracr/compiler/assemble.py
tracr/compiler/assemble_test.py
tracr/compiler/basis_inference.py
tracr/compiler/basis_inference_test.py
tracr/compiler/compiling.py
tracr/compiler/craft_graph_to_model.py
tracr/compiler/craft_graph_to_model_test.py
tracr/compiler/craft_model_to_transformer.py
tracr/compiler/expr_to_craft_graph.py
tracr/compiler/expr_to_craft_graph_test.py
tracr/compiler/lib.py
tracr/compiler/lib_test.py
tracr/compiler/nodes.py
tracr/compiler/rasp_to_craft_integration_test.py
tracr/compiler/rasp_to_graph.py
tracr/compiler/rasp_to_graph_test.py
tracr/compiler/rasp_to_transformer_integration_test.py
tracr/compiler/test_cases.py
tracr/compiler/validating.py
tracr/compiler/validating_test.py
tracr/craft/__init__.py
tracr/craft/bases.py
tracr/craft/bases_test.py
tracr/craft/tests_common.py
tracr/craft/transformers.py
tracr/craft/transformers_test.py
tracr/craft/vectorspace_fns.py
tracr/craft/vectorspace_fns_test.py
tracr/craft/chamber/__init__.py
tracr/craft/chamber/categorical_attn.py
tracr/craft/chamber/categorical_attn_test.py
tracr/craft/chamber/categorical_mlp.py
tracr/craft/chamber/categorical_mlp_test.py
tracr/craft/chamber/numerical_mlp.py
tracr/craft/chamber/numerical_mlp_test.py
tracr/craft/chamber/selector_width.py
tracr/craft/chamber/selector_width_test.py
tracr/examples/__init__.py
tracr/rasp/__init__.py
tracr/rasp/causal_eval.py
tracr/rasp/causal_eval_test.py
tracr/rasp/rasp.py
tracr/rasp/rasp_test.py
tracr/transformer/__init__.py
tracr/transformer/attention.py
tracr/transformer/compressed_model.py
tracr/transformer/compressed_model_test.py
tracr/transformer/encoder.py
tracr/transformer/encoder_test.py
tracr/transformer/model.py
tracr/transformer/model_test.py
tracr/utils/__init__.py
tracr/utils/debugging.py
tracr/utils/errors.py
tracr/utils/errors_test.py
tracr_pypi-1.0.0.dist-info/LICENSE
tracr_pypi-1.0.0.dist-info/METADATA
tracr_pypi-1.0.0.dist-info/WHEEL
tracr_pypi-1.0.0.dist-info/top_level.txt
tracr_pypi-1.0.0.dist-info/RECORD
