Metadata-Version: 2.1
Name: tracr-pypi
Version: 1.0.0
Summary: Compiler from RASP to transformer weights
Home-page: https://github.com/deepmind/tracr
Author: DeepMind LMI team
Author-email: tracr-devs@google.com
License-File: LICENSE
Requires-Dist: chex
Requires-Dist: einops
Requires-Dist: dm-haiku
Requires-Dist: jax
Requires-Dist: networkx
Requires-Dist: numpy
Requires-Dist: typing-extensions
